MANIFEST.in
README.rst
setup.cfg
setup.py
service/__init__.py
service/admin.py
service/apps.py
service/decorators.py
service/models.py
service/tests.py
service/urls.py
service/utils.py
service/views.py
service/migrations/__init__.py
ubox_service.egg-info/PKG-INFO
ubox_service.egg-info/SOURCES.txt
ubox_service.egg-info/dependency_links.txt
ubox_service.egg-info/top_level.txt